cit_images/__init__.py
cit_images/__init__.pyi
cit_images/predict.py
cit_images/reading.py
cit_images-0.1.1.dist-info/METADATA
cit_images-0.1.1.dist-info/WHEEL
cit_images-0.1.1.dist-info/top_level.txt
cit_images-0.1.1.dist-info/RECORD
