Metadata-Version: 2.1
Name: cit-images
Version: 0.1.1
Summary: Tools to access and predict the CIT images
Author-email: Marcel Claramunt <marcel@moveread.com>
Project-URL: repo, https://github.com/moveread/REPO.git
Requires-Python: >=3.10
Requires-Dist: lazy-loader
Provides-Extra: ocr
Requires-Dist: tf-serving ; extra == 'ocr'
